<annotation verified="no">
  <folder>VOC2007</folder>
  <filename>250.jpg</filename>
  <path>/home/lbin/Pictures/VOC2007/250.jpg</path>
  <source>
    <database>Unknown</database>
  </source>
  <size>
    <width>478</width>
    <height>667</height>
    <depth>3</depth>
  </size>
  <segmented>0</segmented>
  <object>
    <name>wangzulan</name>
    <pose>Unspecified</pose>
    <truncated>0</truncated>
    <difficult>0</difficult>
    <bndbox>
      <xmin>191</xmin>
      <ymin>203</ymin>
      <xmax>322</xmax>
      <ymax>314</ymax>
    </bndbox>
  </object>
</annotation>
