<annotation verified="no">
  <folder>spider_download</folder>
  <filename>285.jpg</filename>
  <path>/home/yanweixin/Pictures/spider_download/285.jpg</path>
  <source>
    <database>Unknown</database>
  </source>
  <size>
    <width>703</width>
    <height>1024</height>
    <depth>1</depth>
  </size>
  <segmented>0</segmented>
  <object>
    <name>luhan</name>
    <pose>Unspecified</pose>
    <truncated>0</truncated>
    <difficult>0</difficult>
    <bndbox>
      <xmin>142</xmin>
      <ymin>270</ymin>
      <xmax>483</xmax>
      <ymax>621</ymax>
    </bndbox>
  </object>
</annotation>
